filegram/__init__.py
filegram/send_files.py
filegram-1.2.16.dist-info/LICENSE
filegram-1.2.16.dist-info/METADATA
filegram-1.2.16.dist-info/WHEEL
filegram-1.2.16.dist-info/entry_points.txt
filegram-1.2.16.dist-info/top_level.txt
filegram-1.2.16.dist-info/RECORD
