Metadata-Version: 2.1
Name: filegram
Version: 1.2.16
Summary: A package to send files to Telegram groups
Home-page: https://mrfidal.in/cyber-security/filegram
Author: Fidal
Author-email: mrfidal@proton.me
Keywords: telegram files send
License-File: LICENSE
Requires-Dist: requests
